{
  "fio version" : "fio-3.6-31-g4386",
  "timestamp" : 1547934648,
  "timestamp_ms" : 1547934648179,
  "time" : "Sat Jan 19 22:50:48 2019",
  "jobs" : [
    {
      "jobname" : "random-read",
      "groupid" : 0,
      "error" : 0,
      "eta" : 0,
      "elapsed" : 61,
      "job options" : {
        "rw" : "randread",
        "bs" : "4k",
        "ioengine" : "libaio",
        "iodepth" : "16",
        "direct" : "1",
        "invalidate" : "1",
        "refill_buffers" : "1",
        "runtime" : "60",
        "numjobs" : "1",
        "group_reporting" : "1",
        "write_bw_log" : "random-read-depth-16",
        "write_lat_log" : "random-read-depth-16",
        "write_iops_log" : "random-read-depth-16",
        "log_avg_msec" : "500",
        "filename" : "/dev/rbd0"
      },
      "read" : {
        "io_bytes" : 4240486400,
        "io_kbytes" : 4141100,
        "bw_bytes" : 70672417,
        "bw" : 69016,
        "iops" : 17254.008200,
        "runtime" : 60002,
        "total_ios" : 1035275,
        "short_ios" : 0,
        "drop_ios" : 0,
        "slat_ns" : {
          "min" : 7543,
          "max" : 6163842,
          "mean" : 27329.883605,
          "stddev" : 12130.777779
        },
        "clat_ns" : {
          "min" : 210082,
          "max" : 26979757,
          "mean" : 888481.803630,
          "stddev" : 350332.450462,
          "percentile" : {
            "1.000000" : 440320,
            "5.000000" : 544768,
            "10.000000" : 593920,
            "20.000000" : 667648,
            "30.000000" : 733184,
            "40.000000" : 790528,
            "50.000000" : 839680,
            "60.000000" : 897024,
            "70.000000" : 970752,
            "80.000000" : 1073152,
            "90.000000" : 1220608,
            "95.000000" : 1351680,
            "99.000000" : 1761280,
            "99.500000" : 2007040,
            "99.900000" : 3162112,
            "99.950000" : 6914048,
            "99.990000" : 9502720
          }
        },
        "lat_ns" : {
          "min" : 239416,
          "max" : 27000570,
          "mean" : 918811.979852,
          "stddev" : 349807.408916
        },
        "bw_min" : 64248,
        "bw_max" : 80415,
        "bw_agg" : 99.999795,
        "bw_mean" : 69015.858333,
        "bw_dev" : 2334.133447,
        "bw_samples" : 120,
        "iops_min" : 16062,
        "iops_max" : 20103,
        "iops_mean" : 17253.925000,
        "iops_stddev" : 583.529368,
        "iops_samples" : 120
      },
      "write" : {
        "io_bytes" : 0,
        "io_kbytes" : 0,
        "bw_bytes" : 0,
        "bw" : 0,
        "iops" : 0.000000,
        "runtime" : 0,
        "total_ios" : 0,
        "short_ios" : 0,
        "drop_ios" : 0,
        "slat_ns" : {
          "min" : 0,
          "max" : 0,
          "mean" : 0.000000,
          "stddev" : 0.000000
        },
        "clat_ns" : {
          "min" : 0,
          "max" : 0,
          "mean" : 0.000000,
          "stddev" : 0.000000,
          "percentile" : {
            "1.000000" : 0,
            "5.000000" : 0,
            "10.000000" : 0,
            "20.000000" : 0,
            "30.000000" : 0,
            "40.000000" : 0,
            "50.000000" : 0,
            "60.000000" : 0,
            "70.000000" : 0,
            "80.000000" : 0,
            "90.000000" : 0,
            "95.000000" : 0,
            "99.000000" : 0,
            "99.500000" : 0,
            "99.900000" : 0,
            "99.950000" : 0,
            "99.990000" : 0
          }
        },
        "lat_ns" : {
          "min" : 0,
          "max" : 0,
          "mean" : 0.000000,
          "stddev" : 0.000000
        },
        "bw_min" : 0,
        "bw_max" : 0,
        "bw_agg" : 0.000000,
        "bw_mean" : 0.000000,
        "bw_dev" : 0.000000,
        "bw_samples" : 0,
        "iops_min" : 0,
        "iops_max" : 0,
        "iops_mean" : 0.000000,
        "iops_stddev" : 0.000000,
        "iops_samples" : 0
      },
      "trim" : {
        "io_bytes" : 0,
        "io_kbytes" : 0,
        "bw_bytes" : 0,
        "bw" : 0,
        "iops" : 0.000000,
        "runtime" : 0,
        "total_ios" : 0,
        "short_ios" : 0,
        "drop_ios" : 0,
        "slat_ns" : {
          "min" : 0,
          "max" : 0,
          "mean" : 0.000000,
          "stddev" : 0.000000
        },
        "clat_ns" : {
          "min" : 0,
          "max" : 0,
          "mean" : 0.000000,
          "stddev" : 0.000000,
          "percentile" : {
            "1.000000" : 0,
            "5.000000" : 0,
            "10.000000" : 0,
            "20.000000" : 0,
            "30.000000" : 0,
            "40.000000" : 0,
            "50.000000" : 0,
            "60.000000" : 0,
            "70.000000" : 0,
            "80.000000" : 0,
            "90.000000" : 0,
            "95.000000" : 0,
            "99.000000" : 0,
            "99.500000" : 0,
            "99.900000" : 0,
            "99.950000" : 0,
            "99.990000" : 0
          }
        },
        "lat_ns" : {
          "min" : 0,
          "max" : 0,
          "mean" : 0.000000,
          "stddev" : 0.000000
        },
        "bw_min" : 0,
        "bw_max" : 0,
        "bw_agg" : 0.000000,
        "bw_mean" : 0.000000,
        "bw_dev" : 0.000000,
        "bw_samples" : 0,
        "iops_min" : 0,
        "iops_max" : 0,
        "iops_mean" : 0.000000,
        "iops_stddev" : 0.000000,
        "iops_samples" : 0
      },
      "sync" : {
        "lat_ns" : {
          "min" : 0,
          "max" : 0,
          "mean" : 0.000000,
          "stddev" : 0.000000,
          "percentile" : {
            "1.000000" : 0,
            "5.000000" : 0,
            "10.000000" : 0,
            "20.000000" : 0,
            "30.000000" : 0,
            "40.000000" : 0,
            "50.000000" : 0,
            "60.000000" : 0,
            "70.000000" : 0,
            "80.000000" : 0,
            "90.000000" : 0,
            "95.000000" : 0,
            "99.000000" : 0,
            "99.500000" : 0,
            "99.900000" : 0,
            "99.950000" : 0,
            "99.990000" : 0
          }
        },
        "total_ios" : 0
      },
      "usr_cpu" : 12.853119,
      "sys_cpu" : 30.267829,
      "ctx" : 1246636,
      "majf" : 0,
      "minf" : 36,
      "iodepth_level" : {
        "1" : 0.100000,
        "2" : 0.100000,
        "4" : 0.100000,
        "8" : 0.100000,
        "16" : 99.998551,
        "32" : 0.000000,
        ">=64" : 0.000000
      },
      "latency_ns" : {
        "2" : 0.000000,
        "4" : 0.000000,
        "10" : 0.000000,
        "20" : 0.000000,
        "50" : 0.000000,
        "100" : 0.000000,
        "250" : 0.000000,
        "500" : 0.000000,
        "750" : 0.000000,
        "1000" : 0.000000
      },
      "latency_us" : {
        "2" : 0.000000,
        "4" : 0.000000,
        "10" : 0.000000,
        "20" : 0.000000,
        "50" : 0.000000,
        "100" : 0.000000,
        "250" : 0.010000,
        "500" : 2.639782,
        "750" : 30.433653,
        "1000" : 40.389558
      },
      "latency_ms" : {
        "2" : 26.030765,
        "4" : 0.425491,
        "10" : 0.069547,
        "20" : 0.010000,
        "50" : 0.010000,
        "100" : 0.000000,
        "250" : 0.000000,
        "500" : 0.000000,
        "750" : 0.000000,
        "1000" : 0.000000,
        "2000" : 0.000000,
        ">=2000" : 0.000000
      },
      "latency_depth" : 16,
      "latency_target" : 0,
      "latency_percentile" : 100.000000,
      "latency_window" : 0
    }
  ],
  "disk_util" : [
    {
      "name" : "rbd0",
      "read_ios" : 1032972,
      "write_ios" : 0,
      "read_merges" : 0,
      "write_merges" : 0,
      "read_ticks" : 896576,
      "write_ticks" : 0,
      "in_queue" : 896872,
      "util" : 99.821580
    }
  ]
}
